gradio_image_annotation/__init__.py
gradio_image_annotation/image_annotator.py
gradio_image_annotation/image_annotator.pyi
gradio_image_annotation/templates/component/Index-2rMunfiT.js
gradio_image_annotation/templates/component/_baseUniq-B_y_hkna.js
gradio_image_annotation/templates/component/arc-BJCtvbF3.js
gradio_image_annotation/templates/component/architecture-U656AL7Q-Bwcd1h8b.js
gradio_image_annotation/templates/component/architectureDiagram-VXUJARFQ-DwUVrQQw.js
gradio_image_annotation/templates/component/auto-render-DCrXk9v9.js
gradio_image_annotation/templates/component/blockDiagram-VD42YOAC-D7mIWSs4.js
gradio_image_annotation/templates/component/c4Diagram-YG6GDRKO-IHhRMZP0.js
gradio_image_annotation/templates/component/channel-DwgT34gX.js
gradio_image_annotation/templates/component/chunk-4BX2VUAB-CgbxL9Np.js
gradio_image_annotation/templates/component/chunk-55IACEB6-Ci4f3NnL.js
gradio_image_annotation/templates/component/chunk-B4BG7PRW-BYvD3nIH.js
gradio_image_annotation/templates/component/chunk-DI55MBZ5-rCd-ht5A.js
gradio_image_annotation/templates/component/chunk-FMBD7UC4-Cidqcrl5.js
gradio_image_annotation/templates/component/chunk-QN33PNHL-C3ktT95o.js
gradio_image_annotation/templates/component/chunk-QZHKN3VN-DfoHPLLU.js
gradio_image_annotation/templates/component/chunk-TZMSLE5B-DMjryRGF.js
gradio_image_annotation/templates/component/classDiagram-2ON5EDUG-ChANrd2a.js
gradio_image_annotation/templates/component/classDiagram-v2-WZHVMYZB-ChANrd2a.js
gradio_image_annotation/templates/component/clone-DLiuwsLl.js
gradio_image_annotation/templates/component/cose-bilkent-S5V4N54A-CpOZekD9.js
gradio_image_annotation/templates/component/cytoscape.esm-Cvf3sx9F.js
gradio_image_annotation/templates/component/dagre-6UL2VRFP-B4WG6m9s.js
gradio_image_annotation/templates/component/defaultLocale-BgPVtth8.js
gradio_image_annotation/templates/component/diagram-PSM6KHXK-CFd2TInQ.js
gradio_image_annotation/templates/component/diagram-QEK2KX5R-C-8HHjKc.js
gradio_image_annotation-0.5.0.dist-info/METADATA
gradio_image_annotation-0.5.0.dist-info/WHEEL
gradio_image_annotation-0.5.0.dist-info/licenses/LICENSE
gradio_image_annotation-0.5.0.dist-info/RECORD
